CHANGES.txt
CREDITS.txt
README.txt
TODO.txt
bootstrap.py
buildout.cfg
setup.py
src/z3c/__init__.py
src/z3c.vcsync.egg-info/PKG-INFO
src/z3c.vcsync.egg-info/SOURCES.txt
src/z3c.vcsync.egg-info/dependency_links.txt
src/z3c.vcsync.egg-info/entry_points.txt
src/z3c.vcsync.egg-info/namespace_packages.txt
src/z3c.vcsync.egg-info/not-zip-safe
src/z3c.vcsync.egg-info/requires.txt
src/z3c.vcsync.egg-info/top_level.txt
src/z3c/vcsync/README.txt
src/z3c/vcsync/__init__.py
src/z3c/vcsync/configure.zcml
src/z3c/vcsync/conflict.txt
src/z3c/vcsync/importexport.py
src/z3c/vcsync/importexport.txt
src/z3c/vcsync/interfaces.py
src/z3c/vcsync/internal.txt
src/z3c/vcsync/monkey.py
src/z3c/vcsync/svn.py
src/z3c/vcsync/tests.py
src/z3c/vcsync/type_change.txt
src/z3c/vcsync/vc.py