Metadata-Version: 1.0
Name: z3c.vcsync
Version: 0.17
Summary: Synchronize object data with a version control system
Home-page: UNKNOWN
Author: Martijn Faassen
Author-email: faassen@startifact.com
License: ZPL 2.1
Keywords: zope3 grok web svn synchronization
Platform: UNKNOWN
Classifier: Development Status :: 5 - Production/Stable
Classifier: Environment :: Web Environment
Classifier: Intended Audience :: Developers
Classifier: License :: OSI Approved :: Zope Public License
Classifier: Programming Language :: Python
Classifier: Natural Language :: English
Classifier: Operating System :: OS Independent
Classifier: Topic :: Internet :: WWW/HTTP
Classifier: Framework :: Zope3
